v360_console_utility/__init__.py
v360_console_utility/config.py
v360_console_utility/console.py
v360_console_utility/main.py
v360_console_utility/nas.py
v360_console_utility-0.2.1.dist-info/METADATA
v360_console_utility-0.2.1.dist-info/WHEEL
v360_console_utility-0.2.1.dist-info/entry_points.txt
v360_console_utility-0.2.1.dist-info/RECORD
